antithesis/_assertinfo.py
antithesis/_location.py
antithesis/_tracking.py
antithesis/assertions.py
antithesis/lifecycle.py
antithesis/random.py
antithesis/_internal/__init__.py
antithesis/_internal/handlers.py
antithesis/_internal/sdk_constants.py
antithesis-0.1.18.dist-info/licenses/LICENSE
antithesis-0.1.18.dist-info/METADATA
antithesis-0.1.18.dist-info/WHEEL
antithesis-0.1.18.dist-info/top_level.txt
antithesis-0.1.18.dist-info/RECORD
