Metadata-Version: 2.4
Name: antithesis
Version: 0.1.18
Summary: Antithesis SDK for Python
License: 
Project-URL: homepage, https://antithesis.com/
Project-URL: documentation, https://antithesis.com/docs/
Project-URL: source, https://github.com/antithesishq/antithesis-sdk-python
Project-URL: issues, https://github.com/antithesishq/antithesis-sdk-python/issues
Keywords: antithesis,sdk,autonomous,testing
Classifier: Development Status :: 5 - Production/Stable
Classifier: License :: OSI Approved :: MIT License
Classifier: Operating System :: POSIX
Classifier: Programming Language :: Python :: 3
Classifier: Programming Language :: Python :: 3.9
Classifier: Programming Language :: Python :: 3.10
Classifier: Programming Language :: Python :: 3.11
Classifier: Programming Language :: Python :: 3.12
Classifier: Topic :: Software Development :: Testing
Requires-Python: >=3.9
License-File: LICENSE
Requires-Dist: cffi>=1.16.0
Dynamic: license-file
